npnd/__init__.py
npnd/_src/__init__.py
npnd/_src/config.py
npnd/_src/dtypes.py
npnd/_src/numpy/__init__.py
npnd/_src/ops/__init__.py
npnd/_src/ops/gather_nd.py
npnd/_src/ops/one_hot.py
npnd/_src/ops/values.py
npnd/_src/test_util.py
npnd/errors.py
npnd/numpy/__init__.py
npnd/test_util.py
npnd-0.3.0.dist-info/LICENSE
npnd-0.3.0.dist-info/WHEEL
npnd-0.3.0.dist-info/METADATA
npnd-0.3.0.dist-info/RECORD
